Http2Jiangjie/README.md
Http2Jiangjie/__init__.py
Http2Jiangjie/__main__.py
Http2Jiangjie/file.epub
Http2Jiangjie/index.html
Http2Jiangjie/css/__init__.py
Http2Jiangjie/css/annotations.css
Http2Jiangjie/css/main.css
Http2Jiangjie/css/normalize.css
Http2Jiangjie/css/popup.css
Http2Jiangjie/font/__init__.py
Http2Jiangjie/font/fontello.eot
Http2Jiangjie/font/fontello.svg
Http2Jiangjie/font/fontello.ttf
Http2Jiangjie/font/fontello.woff
Http2Jiangjie/img/__init__.py
Http2Jiangjie/img/annotator-glyph-sprite.png
Http2Jiangjie/img/annotator-icon-sprite.png
Http2Jiangjie/img/apple-touch-icon.png
Http2Jiangjie/img/cancelfullscreen.png
Http2Jiangjie/img/close.png
Http2Jiangjie/img/fullscreen.png
Http2Jiangjie/img/loader.gif
Http2Jiangjie/img/menu-icon.png
Http2Jiangjie/img/save.png
Http2Jiangjie/img/saved.png
Http2Jiangjie/img/settings-s.png
Http2Jiangjie/img/settings.png
Http2Jiangjie/img/star.png
Http2Jiangjie/js/__init__.py
Http2Jiangjie/js/epub.js
Http2Jiangjie/js/epub.min.js
Http2Jiangjie/js/epub.min.map
Http2Jiangjie/js/hooks.min.js
Http2Jiangjie/js/hooks.min.map
Http2Jiangjie/js/reader.js
Http2Jiangjie/js/reader.js.map
Http2Jiangjie/js/reader.min.js
Http2Jiangjie/js/reader.min.map
Http2Jiangjie/js/hooks/__init__.py
Http2Jiangjie/js/hooks/extensions/__init__.py
Http2Jiangjie/js/hooks/extensions/highlight.js
Http2Jiangjie/js/libs/__init__.py
Http2Jiangjie/js/libs/jquery.min.js
Http2Jiangjie/js/libs/localforage.min.js
Http2Jiangjie/js/libs/screenfull.js
Http2Jiangjie/js/libs/screenfull.min.js
Http2Jiangjie/js/libs/zip.min.js
Http2Jiangjie/js/plugins/__init__.py
Http2Jiangjie/js/plugins/hypothesis.js
Http2Jiangjie/js/plugins/search.js
http2_jiangjie-2024.3.1.0.dist-info/METADATA
http2_jiangjie-2024.3.1.0.dist-info/WHEEL
http2_jiangjie-2024.3.1.0.dist-info/entry_points.txt
http2_jiangjie-2024.3.1.0.dist-info/top_level.txt
http2_jiangjie-2024.3.1.0.dist-info/RECORD
